{"nodes": [{"id": "c_users_jeronimo_zapata_documents_github_adminlogisticauv_logistica_app_app_dashboard_health_page_tsx", "label": "page.tsx", "file_type": "code", "source_file": "C:\\Users\\Jeronimo Zapata\\Documents\\GitHub\\adminlogisticauv\\logistica-app\\app\\dashboard\\health\\page.tsx", "source_location": "L1"}, {"id": "health_page_fetchhealth", "label": "fetchHealth()", "file_type": "code", "source_file": "C:\\Users\\Jeronimo Zapata\\Documents\\GitHub\\adminlogisticauv\\logistica-app\\app\\dashboard\\health\\page.tsx", "source_location": "L17"}, {"id": "health_page_servicecard", "label": "ServiceCard()", "file_type": "code", "source_file": "C:\\Users\\Jeronimo Zapata\\Documents\\GitHub\\adminlogisticauv\\logistica-app\\app\\dashboard\\health\\page.tsx", "source_location": "L26"}, {"id": "health_page_healthpage", "label": "HealthPage()", "file_type": "code", "source_file": "C:\\Users\\Jeronimo Zapata\\Documents\\GitHub\\adminlogisticauv\\logistica-app\\app\\dashboard\\health\\page.tsx", "source_location": "L71"}], "edges": [{"source": "c_users_jeronimo_zapata_documents_github_adminlogisticauv_logistica_app_app_dashboard_health_page_tsx", "target": "link", "relation": "imports_from", "context": "import", "confidence": "EXTRACTED", "source_file": "C:\\Users\\Jeronimo Zapata\\Documents\\GitHub\\adminlogisticauv\\logistica-app\\app\\dashboard\\health\\page.tsx", "source_location": "L1", "weight": 1.0}, {"source": "c_users_jeronimo_zapata_documents_github_adminlogisticauv_logistica_app_app_dashboard_health_page_tsx", "target": "lucide_react", "relation": "imports_from", "context": "import", "confidence": "EXTRACTED", "source_file": "C:\\Users\\Jeronimo Zapata\\Documents\\GitHub\\adminlogisticauv\\logistica-app\\app\\dashboard\\health\\page.tsx", "source_location": "L2", "weight": 1.0}, {"source": "c_users_jeronimo_zapata_documents_github_adminlogisticauv_logistica_app_app_dashboard_health_page_tsx", "target": "c_users_jeronimo_zapata_documents_github_adminlogisticauv_logistica_app_app_api_health_route_ts", "relation": "imports_from", "context": "import", "confidence": "EXTRACTED", "source_file": "C:\\Users\\Jeronimo Zapata\\Documents\\GitHub\\adminlogisticauv\\logistica-app\\app\\dashboard\\health\\page.tsx", "source_location": "L3", "weight": 1.0}, {"source": "c_users_jeronimo_zapata_documents_github_adminlogisticauv_logistica_app_app_dashboard_health_page_tsx", "target": "health_route_healthreport", "relation": "imports", "context": "import", "confidence": "EXTRACTED", "source_file": "C:\\Users\\Jeronimo Zapata\\Documents\\GitHub\\adminlogisticauv\\logistica-app\\app\\dashboard\\health\\page.tsx", "source_location": "L3", "weight": 1.0}, {"source": "c_users_jeronimo_zapata_documents_github_adminlogisticauv_logistica_app_app_dashboard_health_page_tsx", "target": "health_route_servicestatus", "relation": "imports", "context": "import", "confidence": "EXTRACTED", "source_file": "C:\\Users\\Jeronimo Zapata\\Documents\\GitHub\\adminlogisticauv\\logistica-app\\app\\dashboard\\health\\page.tsx", "source_location": "L3", "weight": 1.0}, {"source": "c_users_jeronimo_zapata_documents_github_adminlogisticauv_logistica_app_app_dashboard_health_page_tsx", "target": "c_users_jeronimo_zapata_documents_github_adminlogisticauv_logistica_app_src_infrastructure_adapters_healthcheckadapter_ts", "relation": "imports_from", "context": "import", "confidence": "EXTRACTED", "source_file": "C:\\Users\\Jeronimo Zapata\\Documents\\GitHub\\adminlogisticauv\\logistica-app\\app\\dashboard\\health\\page.tsx", "source_location": "L13", "weight": 1.0}, {"source": "c_users_jeronimo_zapata_documents_github_adminlogisticauv_logistica_app_app_dashboard_health_page_tsx", "target": "adapters_healthcheckadapter_gethealthcheckadapter", "relation": "imports", "context": "import", "confidence": "EXTRACTED", "source_file": "C:\\Users\\Jeronimo Zapata\\Documents\\GitHub\\adminlogisticauv\\logistica-app\\app\\dashboard\\health\\page.tsx", "source_location": "L13", "weight": 1.0}, {"source": "c_users_jeronimo_zapata_documents_github_adminlogisticauv_logistica_app_app_dashboard_health_page_tsx", "target": "health_page_fetchhealth", "relation": "contains", "confidence": "EXTRACTED", "source_file": "C:\\Users\\Jeronimo Zapata\\Documents\\GitHub\\adminlogisticauv\\logistica-app\\app\\dashboard\\health\\page.tsx", "source_location": "L17", "weight": 1.0}, {"source": "c_users_jeronimo_zapata_documents_github_adminlogisticauv_logistica_app_app_dashboard_health_page_tsx", "target": "health_page_servicecard", "relation": "contains", "confidence": "EXTRACTED", "source_file": "C:\\Users\\Jeronimo Zapata\\Documents\\GitHub\\adminlogisticauv\\logistica-app\\app\\dashboard\\health\\page.tsx", "source_location": "L26", "weight": 1.0}, {"source": "c_users_jeronimo_zapata_documents_github_adminlogisticauv_logistica_app_app_dashboard_health_page_tsx", "target": "health_page_healthpage", "relation": "contains", "confidence": "EXTRACTED", "source_file": "C:\\Users\\Jeronimo Zapata\\Documents\\GitHub\\adminlogisticauv\\logistica-app\\app\\dashboard\\health\\page.tsx", "source_location": "L71", "weight": 1.0}, {"source": "health_page_healthpage", "target": "health_page_fetchhealth", "relation": "calls", "context": "call", "confidence": "EXTRACTED", "source_file": "C:\\Users\\Jeronimo Zapata\\Documents\\GitHub\\adminlogisticauv\\logistica-app\\app\\dashboard\\health\\page.tsx", "source_location": "L72", "weight": 1.0}], "raw_calls": [{"caller_nid": "health_page_fetchhealth", "callee": "getHealthCheckAdapter", "is_member_call": false, "source_file": "C:\\Users\\Jeronimo Zapata\\Documents\\GitHub\\adminlogisticauv\\logistica-app\\app\\dashboard\\health\\page.tsx", "source_location": "L18"}, {"caller_nid": "health_page_healthpage", "callee": "toLocaleString", "is_member_call": true, "source_file": "C:\\Users\\Jeronimo Zapata\\Documents\\GitHub\\adminlogisticauv\\logistica-app\\app\\dashboard\\health\\page.tsx", "source_location": "L74"}]}