{"nodes": [{"id": "c_users_jeronimo_zapata_documents_github_adminlogisticauv_logistica_app_src_tests_vencimientos_test_ts", "label": "vencimientos.test.ts", "file_type": "code", "source_file": "C:\\Users\\Jeronimo Zapata\\Documents\\GitHub\\adminlogisticauv\\logistica-app\\src\\__tests__\\vencimientos.test.ts", "source_location": "L1"}, {"id": "tests_vencimientos_test_res", "label": "res", "file_type": "code", "source_file": "C:\\Users\\Jeronimo Zapata\\Documents\\GitHub\\adminlogisticauv\\logistica-app\\src\\__tests__\\vencimientos.test.ts", "source_location": "L6"}, {"id": "tests_vencimientos_test_now", "label": "now", "file_type": "code", "source_file": "C:\\Users\\Jeronimo Zapata\\Documents\\GitHub\\adminlogisticauv\\logistica-app\\src\\__tests__\\vencimientos.test.ts", "source_location": "L17"}, {"id": "tests_vencimientos_test_target", "label": "target", "file_type": "code", "source_file": "C:\\Users\\Jeronimo Zapata\\Documents\\GitHub\\adminlogisticauv\\logistica-app\\src\\__tests__\\vencimientos.test.ts", "source_location": "L18"}], "edges": [{"source": "c_users_jeronimo_zapata_documents_github_adminlogisticauv_logistica_app_src_tests_vencimientos_test_ts", "target": "vitest", "relation": "imports_from", "context": "import", "confidence": "EXTRACTED", "source_file": "C:\\Users\\Jeronimo Zapata\\Documents\\GitHub\\adminlogisticauv\\logistica-app\\src\\__tests__\\vencimientos.test.ts", "source_location": "L1", "weight": 1.0}, {"source": "c_users_jeronimo_zapata_documents_github_adminlogisticauv_logistica_app_src_tests_vencimientos_test_ts", "target": "c_users_jeronimo_zapata_documents_github_adminlogisticauv_logistica_app_src_core_domain_calculators_vencimientos_ts", "relation": "imports_from", "context": "import", "confidence": "EXTRACTED", "source_file": "C:\\Users\\Jeronimo Zapata\\Documents\\GitHub\\adminlogisticauv\\logistica-app\\src\\__tests__\\vencimientos.test.ts", "source_location": "L2", "weight": 1.0}, {"source": "c_users_jeronimo_zapata_documents_github_adminlogisticauv_logistica_app_src_tests_vencimientos_test_ts", "target": "calculators_vencimientos_calculartiemporestante", "relation": "imports", "context": "import", "confidence": "EXTRACTED", "source_file": "C:\\Users\\Jeronimo Zapata\\Documents\\GitHub\\adminlogisticauv\\logistica-app\\src\\__tests__\\vencimientos.test.ts", "source_location": "L2", "weight": 1.0}, {"source": "c_users_jeronimo_zapata_documents_github_adminlogisticauv_logistica_app_src_tests_vencimientos_test_ts", "target": "tests_vencimientos_test_res", "relation": "contains", "confidence": "EXTRACTED", "source_file": "C:\\Users\\Jeronimo Zapata\\Documents\\GitHub\\adminlogisticauv\\logistica-app\\src\\__tests__\\vencimientos.test.ts", "source_location": "L6", "weight": 1.0}, {"source": "c_users_jeronimo_zapata_documents_github_adminlogisticauv_logistica_app_src_tests_vencimientos_test_ts", "target": "tests_vencimientos_test_now", "relation": "contains", "confidence": "EXTRACTED", "source_file": "C:\\Users\\Jeronimo Zapata\\Documents\\GitHub\\adminlogisticauv\\logistica-app\\src\\__tests__\\vencimientos.test.ts", "source_location": "L17", "weight": 1.0}, {"source": "c_users_jeronimo_zapata_documents_github_adminlogisticauv_logistica_app_src_tests_vencimientos_test_ts", "target": "tests_vencimientos_test_target", "relation": "contains", "confidence": "EXTRACTED", "source_file": "C:\\Users\\Jeronimo Zapata\\Documents\\GitHub\\adminlogisticauv\\logistica-app\\src\\__tests__\\vencimientos.test.ts", "source_location": "L18", "weight": 1.0}, {"source": "c_users_jeronimo_zapata_documents_github_adminlogisticauv_logistica_app_src_tests_vencimientos_test_ts", "target": "tests_vencimientos_test_res", "relation": "contains", "confidence": "EXTRACTED", "source_file": "C:\\Users\\Jeronimo Zapata\\Documents\\GitHub\\adminlogisticauv\\logistica-app\\src\\__tests__\\vencimientos.test.ts", "source_location": "L20", "weight": 1.0}, {"source": "c_users_jeronimo_zapata_documents_github_adminlogisticauv_logistica_app_src_tests_vencimientos_test_ts", "target": "tests_vencimientos_test_now", "relation": "contains", "confidence": "EXTRACTED", "source_file": "C:\\Users\\Jeronimo Zapata\\Documents\\GitHub\\adminlogisticauv\\logistica-app\\src\\__tests__\\vencimientos.test.ts", "source_location": "L26", "weight": 1.0}, {"source": "c_users_jeronimo_zapata_documents_github_adminlogisticauv_logistica_app_src_tests_vencimientos_test_ts", "target": "tests_vencimientos_test_target", "relation": "contains", "confidence": "EXTRACTED", "source_file": "C:\\Users\\Jeronimo Zapata\\Documents\\GitHub\\adminlogisticauv\\logistica-app\\src\\__tests__\\vencimientos.test.ts", "source_location": "L27", "weight": 1.0}, {"source": "c_users_jeronimo_zapata_documents_github_adminlogisticauv_logistica_app_src_tests_vencimientos_test_ts", "target": "tests_vencimientos_test_res", "relation": "contains", "confidence": "EXTRACTED", "source_file": "C:\\Users\\Jeronimo Zapata\\Documents\\GitHub\\adminlogisticauv\\logistica-app\\src\\__tests__\\vencimientos.test.ts", "source_location": "L29", "weight": 1.0}, {"source": "c_users_jeronimo_zapata_documents_github_adminlogisticauv_logistica_app_src_tests_vencimientos_test_ts", "target": "tests_vencimientos_test_target", "relation": "contains", "confidence": "EXTRACTED", "source_file": "C:\\Users\\Jeronimo Zapata\\Documents\\GitHub\\adminlogisticauv\\logistica-app\\src\\__tests__\\vencimientos.test.ts", "source_location": "L35", "weight": 1.0}, {"source": "c_users_jeronimo_zapata_documents_github_adminlogisticauv_logistica_app_src_tests_vencimientos_test_ts", "target": "tests_vencimientos_test_now", "relation": "contains", "confidence": "EXTRACTED", "source_file": "C:\\Users\\Jeronimo Zapata\\Documents\\GitHub\\adminlogisticauv\\logistica-app\\src\\__tests__\\vencimientos.test.ts", "source_location": "L36", "weight": 1.0}, {"source": "c_users_jeronimo_zapata_documents_github_adminlogisticauv_logistica_app_src_tests_vencimientos_test_ts", "target": "tests_vencimientos_test_res", "relation": "contains", "confidence": "EXTRACTED", "source_file": "C:\\Users\\Jeronimo Zapata\\Documents\\GitHub\\adminlogisticauv\\logistica-app\\src\\__tests__\\vencimientos.test.ts", "source_location": "L38", "weight": 1.0}, {"source": "c_users_jeronimo_zapata_documents_github_adminlogisticauv_logistica_app_src_tests_vencimientos_test_ts", "target": "tests_vencimientos_test_target", "relation": "contains", "confidence": "EXTRACTED", "source_file": "C:\\Users\\Jeronimo Zapata\\Documents\\GitHub\\adminlogisticauv\\logistica-app\\src\\__tests__\\vencimientos.test.ts", "source_location": "L44", "weight": 1.0}, {"source": "c_users_jeronimo_zapata_documents_github_adminlogisticauv_logistica_app_src_tests_vencimientos_test_ts", "target": "tests_vencimientos_test_now", "relation": "contains", "confidence": "EXTRACTED", "source_file": "C:\\Users\\Jeronimo Zapata\\Documents\\GitHub\\adminlogisticauv\\logistica-app\\src\\__tests__\\vencimientos.test.ts", "source_location": "L45", "weight": 1.0}, {"source": "c_users_jeronimo_zapata_documents_github_adminlogisticauv_logistica_app_src_tests_vencimientos_test_ts", "target": "tests_vencimientos_test_res", "relation": "contains", "confidence": "EXTRACTED", "source_file": "C:\\Users\\Jeronimo Zapata\\Documents\\GitHub\\adminlogisticauv\\logistica-app\\src\\__tests__\\vencimientos.test.ts", "source_location": "L47", "weight": 1.0}], "raw_calls": []}